MANIFEST.in
README
setup.py
gen_name.egg-info/PKG-INFO
gen_name.egg-info/SOURCES.txt
gen_name.egg-info/dependency_links.txt
gen_name.egg-info/requires.txt
gen_name.egg-info/top_level.txt
gen_names_ellgreco/__init__.py
gen_names_ellgreco/get_names_ellgreco.py