Metadata-Version: 1.0
Name: gen-name
Version: 0.1.0
Summary: Super useful library
Home-page: https://github.com/treyhunner/names
Author: Ellgreco
Author-email: ellgreco@protonmail.com
License: UNKNOWN
Platform: UNKNOWN
